mzhtool/__init__.py
mzhtool-1.0.5.dist-info/METADATA
mzhtool-1.0.5.dist-info/WHEEL
mzhtool-1.0.5.dist-info/RECORD
