Metadata-Version: 2.4
Name: mzhtool
Version: 1.0.5
Summary: 个人工具包
Project-URL: Homepage, http://xxx.xxx.xxx
Author-email: name <191891173@qq.com>
Classifier: License :: OSI Approved :: MIT License
Classifier: Operating System :: OS Independent
Classifier: Programming Language :: Python :: 3
Requires-Python: >=3.6
